rag_agent/__init__.py
rag_agent/pipeline/__init__.py
rag_agent/pipeline/__main__.py
rag_agent/pipeline/base.py
rag_agent/pipeline/config.py
rag_agent/pipeline/chroma/__init__.py
rag_agent/pipeline/chroma/config.py
rag_agent/pipeline/chroma/vectorstore.py
rag_agent/scrapers/__init__.py
rag_agent/scrapers/ix/__init__.py
rag_agent/scrapers/ix/__main__.py
rag_agent/scrapers/ix/article.py
rag_agent/scrapers/ix/config.py
rag_agent/scrapers/ix/downloader.py
rag_agent/scrapers/ix/scraper.py
rag_agent/ui/__init__.py
rag_agent/ui/__main__.py
rag_agent/utils/__init__.py
rag_agent/utils/merge/__init__.py
rag_agent/utils/merge/__main__.py
rag_agent-0.3.0.dist-info/licenses/LICENSE
rag_agent-0.3.0.dist-info/METADATA
rag_agent-0.3.0.dist-info/WHEEL
rag_agent-0.3.0.dist-info/entry_points.txt
rag_agent-0.3.0.dist-info/top_level.txt
rag_agent-0.3.0.dist-info/RECORD
