Metadata-Version: 2.4
Name: rag-agent
Version: 0.3.0
Summary: RAG (Retrieval-Augmented Generation) pipeline implementation
Author-email: Dawid Ciepiela <71898979+sarumaj@users.noreply.github.com>
License: MIT
Classifier: Programming Language :: Python :: 3.12
Classifier: License :: OSI Approved :: MIT License
Classifier: Operating System :: OS Independent
Requires-Python: >=3.12
License-File: LICENSE
Requires-Dist: aiohttp==3.11.18
Requires-Dist: asyncio==3.4.3
Requires-Dist: beautifulsoup4==4.13.4
Requires-Dist: langchain==0.3.25
Requires-Dist: langchain-chroma==0.2.3
Requires-Dist: langchain-community==0.3.23
Requires-Dist: langchain-core==0.3.58
Requires-Dist: langchain-huggingface==0.1.2
Requires-Dist: langchain-ollama==0.3.2
Requires-Dist: langchain-text-splitters==0.3.8
Requires-Dist: langgraph==0.4.1
Requires-Dist: nest-asyncio==1.6.0
Requires-Dist: pydantic==2.11.4
Requires-Dist: pydantic-settings==2.9.1
Requires-Dist: tqdm==4.67.1
Provides-Extra: loaders
Requires-Dist: pymupdf==1.25.5; extra == "loaders"
Requires-Dist: unstructured==0.17.2; extra == "loaders"
Provides-Extra: scraper
Requires-Dist: selenium==4.32.0; extra == "scraper"
Requires-Dist: webdriver_manager==4.0.2; extra == "scraper"
Provides-Extra: test
Requires-Dist: pytest==8.0.0; extra == "test"
Requires-Dist: pytest-asyncio==0.23.5; extra == "test"
Provides-Extra: ui
Requires-Dist: panel==1.7.0; extra == "ui"
Requires-Dist: Pygments==2.19.1; extra == "ui"
Dynamic: license-file
